dkvaultutils/__init__.py
dkvaultutils/vault.py
dkvaultutils/vault_lib.py
dkvaultutils/vlt.py
dkvaultutils-0.0.10.dist-info/METADATA
dkvaultutils-0.0.10.dist-info/WHEEL
dkvaultutils-0.0.10.dist-info/top_level.txt
dkvaultutils-0.0.10.dist-info/zip-safe
dkvaultutils-0.0.10.dist-info/RECORD
