Metadata-Version: 2.4
Name: dkvaultutils
Version: 0.0.10
Summary: Common utils and access libs and patterns for dagknows vault access
Home-page: https://github.com/dagknows/dkvaultutils
Author: Sriram Panyam
Author-email: sri@dagknows.com
License: BSD 3-Clause License
Keywords: deployment tools,cli,api,setuptools
Classifier: License :: OSI Approved :: BSD License
Classifier: Programming Language :: Python :: 3
Requires-Dist: requests
Requires-Dist: hvac
Requires-Dist: pywinrm
Requires-Dist: typer[all]
